slim_gym/__init__.py
slim_gym/envs/base_env.py
slim_gym/envs/make_sfs_env.py
slim_gym/envs/sfs_env.py
slim_gym/examples/SB3_PPO_bottleneck.py
slim_gym/scripts/bottleneck.slim
slim_gym/scripts/growth.slim
slim_gym/utils/utils.py
slim_gym-0.3.0.dist-info/licenses/LICENSE.txt
slim_gym-0.3.0.dist-info/WHEEL
slim_gym-0.3.0.dist-info/METADATA
slim_gym-0.3.0.dist-info/RECORD
