Metadata-Version: 2.4
Name: slim_gym
Version: 0.3.0
Summary: @author: nzupp
Author-email: Niko Zuppas <zuppas.3@osu.edu>
License-File: LICENSE.txt
Requires-Dist: gymnasium==1.0.0
Requires-Dist: matplotlib==3.10.0
Requires-Dist: numpy==1.26.4
Requires-Dist: stable-baselines3
Requires-Dist: setuptools
Project-URL: Home, https://github.com/nzupp/SLiM-Gym
